flower_i18n/__init__.py
flower_i18n/i18n.py
flower_i18n/patcher.py
flower_i18n/locales/en_US/messages.json
flower_i18n/locales/zh_CN/messages.json
flower_i18n/static/js/i18n.js
flower_i18n-0.1.2.dist-info/licenses/LICENSE
flower_i18n-0.1.2.dist-info/METADATA
flower_i18n-0.1.2.dist-info/WHEEL
flower_i18n-0.1.2.dist-info/entry_points.txt
flower_i18n-0.1.2.dist-info/top_level.txt
flower_i18n-0.1.2.dist-info/RECORD
