Metadata-Version: 2.4
Name: flower-i18n
Version: 0.1.2
Summary: Internationalization (i18n) support for Flower Celery monitoring tool
Author-email: "邹长林 (Zou Changlin)" <zchanglin@163.com>
License: MIT
Project-URL: Homepage, https://github.com/zouchanglin/flower-i18n
Project-URL: Documentation, https://github.com/zouchanglin/flower-i18n#readme
Project-URL: Repository, https://github.com/zouchanglin/flower-i18n.git
Project-URL: Bug Tracker, https://github.com/zouchanglin/flower-i18n/issues
Keywords: flower,celery,i18n,internationalization,monitoring
Classifier: Development Status :: 3 - Alpha
Classifier: Intended Audience :: Developers
Classifier: License :: OSI Approved :: MIT License
Classifier: Programming Language :: Python :: 3
Classifier: Programming Language :: Python :: 3.8
Classifier: Programming Language :: Python :: 3.9
Classifier: Programming Language :: Python :: 3.10
Classifier: Programming Language :: Python :: 3.11
Classifier: Programming Language :: Python :: 3.12
Classifier: Topic :: Software Development :: Internationalization
Classifier: Topic :: System :: Monitoring
Requires-Python: >=3.8
License-File: LICENSE
Requires-Dist: flower>=2.0.0
Requires-Dist: tornado>=6.0
Provides-Extra: dev
Requires-Dist: pytest>=7.0; extra == "dev"
Requires-Dist: pytest-cov>=4.0; extra == "dev"
Requires-Dist: black>=22.0; extra == "dev"
Requires-Dist: flake8>=6.0; extra == "dev"
Requires-Dist: mypy>=1.0; extra == "dev"
Dynamic: license-file
